{"type":"FeatureCollection","features":[{"type":"Feature","properties":{"name":"Спасите"},
"geometry":{"coordinates":[107.90024560511569,46.914886065861566],"type":"Point"},"id":0},
{"type":"Feature","properties":{"name":"Помогите"},"geometry":{"coordinates":[107.46033729356276,47.85183032572439],"type":"Point"},"id":1}]}
