{
  "type": "FeatureCollection",
  "features": [
    {
      "type": "Feature",
      "properties": {
        "name": "Пример кладбища 1"
      },
      "geometry": {
        "type": "Point",
        "coordinates": [107.90024560511569, 46.914886065861566]
      },
      "id": 0
    },
    {
      "type": "Feature",
      "properties": {
        "name": "Пример кладбища 2"
      },
      "geometry": {
        "type": "Point",
        "coordinates": [107.46033729356276, 47.85183032572439]
      },
      "id": 1
    },
    {
      "type": "Feature",
      "properties": {
        "name": "Пример кладбища 3"
      },
      "geometry": {
        "type": "Point",
        "coordinates": []
      },
      "id": 1
    }
  ]
}


